agentgpt/main.py
agentgpt-0.0.2.dist-info/METADATA
agentgpt-0.0.2.dist-info/WHEEL
agentgpt-0.0.2.dist-info/RECORD
